Metadata-Version: 1.0
Name: tomdistr
Version: 0.1
Summary: Gaussian distributions
Home-page: UNKNOWN
Author: Tom Mathew
Author-email: something@nothing.com
License: UNKNOWN
Platform: UNKNOWN
